{"config":{"sensorType":"SS49E","analogPin":13,"measurementInterval":1000,"uploadInterval":60000},"uptime":121,"readings":[{"timestamp":71,"magneticField":-0.764337},{"timestamp":72,"magneticField":-0.764337},{"timestamp":73,"magneticField":-0.764337},{"timestamp":74,"magneticField":-0.764337},{"timestamp":75,"magneticField":-0.764337},{"timestamp":76,"magneticField":-0.764337},{"timestamp":77,"magneticField":-0.764337},{"timestamp":78,"magneticField":-0.764337},{"timestamp":79,"magneticField":-0.764337},{"timestamp":80,"magneticField":-0.764337},{"timestamp":81,"magneticField":-0.764337},{"timestamp":82,"magneticField":-0.764337},{"timestamp":83,"magneticField":-0.764337},{"timestamp":84,"magneticField":-0.764337},{"timestamp":85,"magneticField":-0.764337},{"timestamp":86,"magneticField":-0.764337},{"timestamp":87,"magneticField":-0.764337},{"timestamp":88,"magneticField":-0.764337},{"timestamp":89,"magneticField":-0.764337},{"timestamp":90,"magneticField":-0.764337},{"timestamp":91,"magneticField":-0.764337},{"timestamp":92,"magneticField":-0.764337},{"timestamp":93,"magneticField":-0.764337},{"timestamp":94,"magneticField":-0.764337},{"timestamp":95,"magneticField":-0.764337},{"timestamp":96,"magneticField":-0.764337},{"timestamp":97,"magneticField":-0.764337},{"timestamp":98,"magneticField":-0.764337},{"timestamp":99,"magneticField":-0.764337},{"timestamp":100,"magneticField":-0.764337},{"timestamp":101,"magneticField":-0.764337},{"timestamp":102,"magneticField":-0.764337},{"timestamp":103,"magneticField":-0.764337},{"timestamp":104,"magneticField":-0.764337},{"timestamp":105,"magneticField":-0.764337},{"timestamp":106,"magneticField":-0.764337},{"timestamp":107,"magneticField":-0.764337},{"timestamp":108,"magneticField":-0.764337},{"timestamp":109,"magneticField":-0.764337},{"timestamp":110,"magneticField":-0.764337},{"timestamp":111,"magneticField":-0.764337},{"timestamp":112,"magneticField":-0.764337},{"timestamp":113,"magneticField":-0.764337},{"timestamp":114,"magneticField":-0.764337},{"timestamp":115,"magneticField":-0.764337},{"timestamp":116,"magneticField":-0.764337},{"timestamp":117,"magneticField":-0.764337},{"timestamp":118,"magneticField":-0.764337},{"timestamp":119,"magneticField":-0.764337},{"timestamp":54,"magneticField":-0.764337},{"timestamp":55,"magneticField":-0.764337},{"timestamp":56,"magneticField":-0.764337},{"timestamp":57,"magneticField":-0.764337},{"timestamp":58,"magneticField":-0.764337},{"timestamp":59,"magneticField":-0.764337},{"timestamp":66,"magneticField":-0.764337},{"timestamp":67,"magneticField":-0.764337},{"timestamp":68,"magneticField":-0.764337},{"timestamp":69,"magneticField":-0.764337},{"timestamp":70,"magneticField":-0.764337}]}